src/config.py
src/crypt/__init__.py
src/crypt/in_memory.py
src/kondar.py
src/main.py
src/storage/keys.txt
kondar_guard-0.1.0.dist-info/METADATA
kondar_guard-0.1.0.dist-info/WHEEL
kondar_guard-0.1.0.dist-info/entry_points.txt
kondar_guard-0.1.0.dist-info/RECORD
