Metadata-Version: 2.1
Name: kondar-guard
Version: 0.1.0
Summary: A console program for secure data storage
Author: nkdo
Author-email: fofmow@gmail.com
Requires-Python: >=3.9,<4.0
Classifier: Programming Language :: Python :: 3
Classifier: Programming Language :: Python :: 3.9
Classifier: Programming Language :: Python :: 3.10
Classifier: Programming Language :: Python :: 3.11
Classifier: Programming Language :: Python :: 3.12
Requires-Dist: colorama (>=0.4.6,<0.5.0)
Requires-Dist: pyaescrypt (>=6.1.1,<7.0.0)
